{"otherData": {},"traceEvents":[{},{"cat":"function","dur":62341,"name":"glfwInit","ph":"X","pid":0,"tid":14836,"ts":31885392310.000},{"cat":"function","dur":583084,"name":"glfwCreateWindow","ph":"X","pid":0,"tid":14836,"ts":31885463540.500},{"cat":"function","dur":3633,"name":"void __cdecl Kaidel::OpenGLContext::Init(void)","ph":"X","pid":0,"tid":14836,"ts":31886048317.400},{"cat":"function","dur":27,"name":"void __cdecl Kaidel::WindowsWindow::SetVSync(bool)","ph":"X","pid":0,"tid":14836,"ts":31886052037.200},{"cat":"function","dur":665394,"name":"void __cdecl Kaidel::WindowsWindow::Init(const struct Kaidel::WindowProps &)","ph":"X","pid":0,"tid":14836,"ts":31885387705.100},{"cat":"function","dur":665492,"name":"__cdecl Kaidel::WindowsWindow::WindowsWindow(const struct Kaidel::WindowProps &)","ph":"X","pid":0,"tid":14836,"ts":31885387701.000},{"cat":"function","dur":11,"name":"void __cdecl Kaidel::OpenGLRendererAPI::Init(void)","ph":"X","pid":0,"tid":14836,"ts":31886054623.600},{"cat":"function","dur":8,"name":"__cdecl Kaidel::OpenGLVertexArray::OpenGLVertexArray(void)","ph":"X","pid":0,"tid":14836,"ts":31886054775.100},{"cat":"function","dur":76,"name":"__cdecl Kaidel::OpenGLVertexBuffer::OpenGLVertexBuffer(unsigned int)","ph":"X","pid":0,"tid":14836,"ts":31886054855.800},{"cat":"function","dur":1,"name":"void __cdecl Kaidel::OpenGLVertexBuffer::Bind(void) const","ph":"X","pid":0,"tid":14836,"ts":31886055040.300},{"cat":"function","dur":69,"name":"void __cdecl Kaidel::OpenGLVertexArray::AddVertexBuffer(const class std::shared_ptr<class Kaidel::VertexBuffer> &)","ph":"X","pid":0,"tid":14836,"ts":31886055038.600},{"cat":"function","dur":914,"name":"__cdecl Kaidel::OpenGLIndexBuffer::OpenGLIndexBuffer(unsigned int *,unsigned int)","ph":"X","pid":0,"tid":14836,"ts":31886057061.900},{"cat":"function","dur":2,"name":"void __cdecl Kaidel::OpenGLIndexBuffer::Bind(void) const","ph":"X","pid":0,"tid":14836,"ts":31886058139.000},{"cat":"function","dur":55,"name":"void __cdecl Kaidel::OpenGLVertexArray::SetIndexBuffer(const class std::shared_ptr<class Kaidel::IndexBuffer> &)","ph":"X","pid":0,"tid":14836,"ts":31886058131.000},{"cat":"function","dur":14,"name":"__cdecl Kaidel::OpenGLVertexArray::OpenGLVertexArray(void)","ph":"X","pid":0,"tid":14836,"ts":31886058295.000},{"cat":"function","dur":34,"name":"__cdecl Kaidel::OpenGLVertexBuffer::OpenGLVertexBuffer(unsigned int)","ph":"X","pid":0,"tid":14836,"ts":31886058355.100},{"cat":"function","dur":1,"name":"void __cdecl Kaidel::OpenGLVertexBuffer::Bind(void) const","ph":"X","pid":0,"tid":14836,"ts":31886058508.900},{"cat":"function","dur":107,"name":"void __cdecl Kaidel::OpenGLVertexArray::AddVertexBuffer(const class std::shared_ptr<class Kaidel::VertexBuffer> &)","ph":"X","pid":0,"tid":14836,"ts":31886058453.100},{"cat":"function","dur":1,"name":"void __cdecl Kaidel::OpenGLIndexBuffer::Bind(void) const","ph":"X","pid":0,"tid":14836,"ts":31886058599.800},{"cat":"function","dur":39,"name":"void __cdecl Kaidel::OpenGLVertexArray::SetIndexBuffer(const class std::shared_ptr<class Kaidel::IndexBuffer> &)","ph":"X","pid":0,"tid":14836,"ts":31886058597.000},{"cat":"function","dur":12,"name":"__cdecl Kaidel::OpenGLVertexArray::OpenGLVertexArray(void)","ph":"X","pid":0,"tid":14836,"ts":31886060537.500},{"cat":"function","dur":55,"name":"__cdecl Kaidel::OpenGLVertexBuffer::OpenGLVertexBuffer(unsigned int)","ph":"X","pid":0,"tid":14836,"ts":31886060704.700},{"cat":"function","dur":0,"name":"void __cdecl Kaidel::OpenGLVertexBuffer::Bind(void) const","ph":"X","pid":0,"tid":14836,"ts":31886060834.400},{"cat":"function","dur":55,"name":"void __cdecl Kaidel::OpenGLVertexArray::AddVertexBuffer(const class std::shared_ptr<class Kaidel::VertexBuffer> &)","ph":"X","pid":0,"tid":14836,"ts":31886060831.600},{"cat":"function","dur":339,"name":"__cdecl Kaidel::OpenGLTexture2D::OpenGLTexture2D(unsigned int,unsigned int)","ph":"X","pid":0,"tid":14836,"ts":31886061898.800},{"cat":"function","dur":96,"name":"void __cdecl Kaidel::OpenGLTexture2D::SetData(void *,unsigned int)","ph":"X","pid":0,"tid":14836,"ts":31886062770.100},{"cat":"function","dur":1652,"name":"class std::basic_string<char,struct std::char_traits<char>,class std::allocator<char> > __cdecl Kaidel::OpenGLShader::ReadFile(const class std::basic_string<char,struct std::char_traits<char>,class std::allocator<char> > &)","ph":"X","pid":0,"tid":14836,"ts":31886063167.300},{"cat":"function","dur":751,"name":"class std::unordered_map<unsigned int,class std::basic_string<char,struct std::char_traits<char>,class std::allocator<char> >,struct std::hash<unsigned int>,struct std::equal_to<unsigned int>,class std::allocator<struct std::pair<unsigned int const ,class std::basic_string<char,struct std::char_traits<char>,class std::allocator<char> > > > > __cdecl Kaidel::OpenGLShader::PreProcess(const class std::basic_string<char,struct std::char_traits<char>,class std::allocator<char> > &)","ph":"X","pid":0,"tid":14836,"ts":31886064963.000},{"cat":"function","dur":5884,"name":"void __cdecl Kaidel::OpenGLShader::Compile(const class std::unordered_map<unsigned int,class std::basic_string<char,struct std::char_traits<char>,class std::allocator<char> >,struct std::hash<unsigned int>,struct std::equal_to<unsigned int>,class std::allocator<struct std::pair<unsigned int const ,class std::basic_string<char,struct std::char_traits<char>,class std::allocator<char> > > > > &)","ph":"X","pid":0,"tid":14836,"ts":31886065822.000},{"cat":"function","dur":8709,"name":"__cdecl Kaidel::OpenGLShader::OpenGLShader(const class std::basic_string<char,struct std::char_traits<char>,class std::allocator<char> > &)","ph":"X","pid":0,"tid":14836,"ts":31886063134.800},{"cat":"function","dur":865,"name":"class std::basic_string<char,struct std::char_traits<char>,class std::allocator<char> > __cdecl Kaidel::OpenGLShader::ReadFile(const class std::basic_string<char,struct std::char_traits<char>,class std::allocator<char> > &)","ph":"X","pid":0,"tid":14836,"ts":31886071897.800},{"cat":"function","dur":28,"name":"class std::unordered_map<unsigned int,class std::basic_string<char,struct std::char_traits<char>,class std::allocator<char> >,struct std::hash<unsigned int>,struct std::equal_to<unsigned int>,class std::allocator<struct std::pair<unsigned int const ,class std::basic_string<char,struct std::char_traits<char>,class std::allocator<char> > > > > __cdecl Kaidel::OpenGLShader::PreProcess(const class std::basic_string<char,struct std::char_traits<char>,class std::allocator<char> > &)","ph":"X","pid":0,"tid":14836,"ts":31886072854.000},{"cat":"function","dur":340,"name":"void __cdecl Kaidel::OpenGLShader::Compile(const class std::unordered_map<unsigned int,class std::basic_string<char,struct std::char_traits<char>,class std::allocator<char> >,struct std::hash<unsigned int>,struct std::equal_to<unsigned int>,class std::allocator<struct std::pair<unsigned int const ,class std::basic_string<char,struct std::char_traits<char>,class std::allocator<char> > > > > &)","ph":"X","pid":0,"tid":14836,"ts":31886072928.800},{"cat":"function","dur":1432,"name":"__cdecl Kaidel::OpenGLShader::OpenGLShader(const class std::basic_string<char,struct std::char_traits<char>,class std::allocator<char> > &)","ph":"X","pid":0,"tid":14836,"ts":31886071897.500},{"cat":"function","dur":741,"name":"class std::basic_string<char,struct std::char_traits<char>,class std::allocator<char> > __cdecl Kaidel::OpenGLShader::ReadFile(const class std::basic_string<char,struct std::char_traits<char>,class std::allocator<char> > &)","ph":"X","pid":0,"tid":14836,"ts":31886073374.500},{"cat":"function","dur":22,"name":"class std::unordered_map<unsigned int,class std::basic_string<char,struct std::char_traits<char>,class std::allocator<char> >,struct std::hash<unsigned int>,struct std::equal_to<unsigned int>,class std::allocator<struct std::pair<unsigned int const ,class std::basic_string<char,struct std::char_traits<char>,class std::allocator<char> > > > > __cdecl Kaidel::OpenGLShader::PreProcess(const class std::basic_string<char,struct std::char_traits<char>,class std::allocator<char> > &)","ph":"X","pid":0,"tid":14836,"ts":31886074197.500},{"cat":"function","dur":329,"name":"void __cdecl Kaidel::OpenGLShader::Compile(const class std::unordered_map<unsigned int,class std::basic_string<char,struct std::char_traits<char>,class std::allocator<char> >,struct std::hash<unsigned int>,struct std::equal_to<unsigned int>,class std::allocator<struct std::pair<unsigned int const ,class std::basic_string<char,struct std::char_traits<char>,class std::allocator<char> > > > > &)","ph":"X","pid":0,"tid":14836,"ts":31886074264.500},{"cat":"function","dur":1315,"name":"__cdecl Kaidel::OpenGLShader::OpenGLShader(const class std::basic_string<char,struct std::char_traits<char>,class std::allocator<char> > &)","ph":"X","pid":0,"tid":14836,"ts":31886073374.300},{"cat":"function","dur":21260,"name":"void __cdecl Kaidel::Renderer2D::Init(void)","ph":"X","pid":0,"tid":14836,"ts":31886054727.200},{"cat":"function","dur":21501,"name":"void __cdecl Kaidel::Renderer::Init(void)","ph":"X","pid":0,"tid":14836,"ts":31886054598.500},{"cat":"function","dur":5831,"name":"void __cdecl Kaidel::ImGuiLayer::OnAttach(void)","ph":"X","pid":0,"tid":14836,"ts":31886077047.900},{"cat":"function","dur":5940,"name":"void __cdecl Kaidel::Application::PushOverlay(class Kaidel::Layer *)","ph":"X","pid":0,"tid":14836,"ts":31886077033.000},{"cat":"function","dur":695753,"name":"__cdecl Kaidel::Application::Application(const class std::basic_string<char,struct std::char_traits<char>,class std::allocator<char> > &)","ph":"X","pid":0,"tid":14836,"ts":31885387261.900},{"cat":"function","dur":9,"name":"__cdecl Kaidel::OrthographicCamera::OrthographicCamera(float,float,float,float)","ph":"X","pid":0,"tid":14836,"ts":31886083951.000},{"cat":"function","dur":2066,"name":"stbi_load - OpenGLTexture2D::OpenGLTexture2D(const std::string&)","ph":"X","pid":0,"tid":14836,"ts":31886084053.800},{"cat":"function","dur":2202,"name":"__cdecl Kaidel::OpenGLTexture2D::OpenGLTexture2D(const class std::basic_string<char,struct std::char_traits<char>,class std::allocator<char> > &)","ph":"X","pid":0,"tid":14836,"ts":31886084046.800},{"cat":"function","dur":411,"name":"stbi_load - OpenGLTexture2D::OpenGLTexture2D(const std::string&)","ph":"X","pid":0,"tid":14836,"ts":31886086308.100},{"cat":"function","dur":523,"name":"__cdecl Kaidel::OpenGLTexture2D::OpenGLTexture2D(const class std::basic_string<char,struct std::char_traits<char>,class std::allocator<char> > &)","ph":"X","pid":0,"tid":14836,"ts":31886086307.900},{"cat":"function","dur":770,"name":"stbi_load - OpenGLTexture2D::OpenGLTexture2D(const std::string&)","ph":"X","pid":0,"tid":14836,"ts":31886086919.900},{"cat":"function","dur":878,"name":"__cdecl Kaidel::OpenGLTexture2D::OpenGLTexture2D(const class std::basic_string<char,struct std::char_traits<char>,class std::allocator<char> > &)","ph":"X","pid":0,"tid":14836,"ts":31886086919.800},{"cat":"function","dur":444,"name":"stbi_load - OpenGLTexture2D::OpenGLTexture2D(const std::string&)","ph":"X","pid":0,"tid":14836,"ts":31886087854.200},{"cat":"function","dur":541,"name":"__cdecl Kaidel::OpenGLTexture2D::OpenGLTexture2D(const class std::basic_string<char,struct std::char_traits<char>,class std::allocator<char> > &)","ph":"X","pid":0,"tid":14836,"ts":31886087854.100},{"cat":"function","dur":407,"name":"stbi_load - OpenGLTexture2D::OpenGLTexture2D(const std::string&)","ph":"X","pid":0,"tid":14836,"ts":31886088450.300},{"cat":"function","dur":495,"name":"__cdecl Kaidel::OpenGLTexture2D::OpenGLTexture2D(const class std::basic_string<char,struct std::char_traits<char>,class std::allocator<char> > &)","ph":"X","pid":0,"tid":14836,"ts":31886088450.100},{"cat":"function","dur":383,"name":"stbi_load - OpenGLTexture2D::OpenGLTexture2D(const std::string&)","ph":"X","pid":0,"tid":14836,"ts":31886089014.200},{"cat":"function","dur":477,"name":"__cdecl Kaidel::OpenGLTexture2D::OpenGLTexture2D(const class std::basic_string<char,struct std::char_traits<char>,class std::allocator<char> > &)","ph":"X","pid":0,"tid":14836,"ts":31886089014.100},{"cat":"function","dur":182,"name":"stbi_load - OpenGLTexture2D::OpenGLTexture2D(const std::string&)","ph":"X","pid":0,"tid":14836,"ts":31886089561.200},{"cat":"function","dur":271,"name":"__cdecl Kaidel::OpenGLTexture2D::OpenGLTexture2D(const class std::basic_string<char,struct std::char_traits<char>,class std::allocator<char> > &)","ph":"X","pid":0,"tid":14836,"ts":31886089561.100},{"cat":"function","dur":8028,"name":"void __cdecl Kaidel::EditorLayer::OnAttach(void)","ph":"X","pid":0,"tid":14836,"ts":31886086916.400},{"cat":"function","dur":8154,"name":"void __cdecl Kaidel::Application::PushLayer(class Kaidel::Layer *)","ph":"X","pid":0,"tid":14836,"ts":31886086910.600}]}